<?xml version="1.0" encoding="utf-8" ?>
<areapionts>
    	    <areapiont>
			<year>2016</year>
			<specialname>法学类（法学）</specialname>
			<maxfs>535</maxfs>
			<varfs>507</varfs>
			<minfs>501</minfs>
			<pc>一批</pc>
			<stype>文科</stype>
		</areapiont>
	    <areapiont>
			<year>2016</year>
			<specialname>工商管理类（管理学Ⅱ）</specialname>
			<maxfs>526</maxfs>
			<varfs>507</varfs>
			<minfs>501</minfs>
			<pc>一批</pc>
			<stype>文科</stype>
		</areapiont>
	    <areapiont>
			<year>2016</year>
			<specialname>法学类</specialname>
			<maxfs>--</maxfs>
			<varfs>521</varfs>
			<minfs>--</minfs>
			<pc>一批</pc>
			<stype>文科</stype>
		</areapiont>
	    <areapiont>
			<year>2016</year>
			<specialname>工商管理类</specialname>
			<maxfs>--</maxfs>
			<varfs>517</varfs>
			<minfs>--</minfs>
			<pc>一批</pc>
			<stype>文科</stype>
		</areapiont>
	    <areapiont>
			<year>2014</year>
			<specialname>工商管理类</specialname>
			<maxfs>592</maxfs>
			<varfs>592</varfs>
			<minfs>591</minfs>
			<pc>一批</pc>
			<stype>文科</stype>
		</areapiont>
	    <areapiont>
			<year>2014</year>
			<specialname>行政管理</specialname>
			<maxfs>587</maxfs>
			<varfs>584</varfs>
			<minfs>582</minfs>
			<pc>一批</pc>
			<stype>文科</stype>
		</areapiont>
	    <areapiont>
			<year>2013</year>
			<specialname>人力资源管理</specialname>
			<maxfs>538</maxfs>
			<varfs>531</varfs>
			<minfs>--</minfs>
			<pc>一批</pc>
			<stype>文科</stype>
		</areapiont>
	    <areapiont>
			<year>2013</year>
			<specialname>英语</specialname>
			<maxfs>539</maxfs>
			<varfs>534</varfs>
			<minfs>--</minfs>
			<pc>一批</pc>
			<stype>文科</stype>
		</areapiont>
	    <areapiont>
			<year>2012</year>
			<specialname>农林经济管理</specialname>
			<maxfs>574</maxfs>
			<varfs>570</varfs>
			<minfs>--</minfs>
			<pc>一批</pc>
			<stype>文科</stype>
		</areapiont>
	    <areapiont>
			<year>2011</year>
			<specialname>行政管理</specialname>
			<maxfs>572</maxfs>
			<varfs>568</varfs>
			<minfs>0</minfs>
			<pc>一批</pc>
			<stype>文科</stype>
		</areapiont>
	    <areapiont>
			<year>2010</year>
			<specialname>农林经济管理</specialname>
			<maxfs>557</maxfs>
			<varfs>557</varfs>
			<minfs>--</minfs>
			<pc>一批</pc>
			<stype>文科</stype>
		</areapiont>
	    <areapiont>
			<year>2010</year>
			<specialname>英语</specialname>
			<maxfs>562</maxfs>
			<varfs>562</varfs>
			<minfs>--</minfs>
			<pc>一批</pc>
			<stype>文科</stype>
		</areapiont>
	    <areapiont>
			<year>2009</year>
			<specialname>英语</specialname>
			<maxfs>582</maxfs>
			<varfs>582</varfs>
			<minfs>--</minfs>
			<pc>一批</pc>
			<stype>文科</stype>
		</areapiont>
	    <areapiont>
			<year>2009</year>
			<specialname>会计学</specialname>
			<maxfs>584</maxfs>
			<varfs>584</varfs>
			<minfs>--</minfs>
			<pc>一批</pc>
			<stype>文科</stype>
		</areapiont>
	    <areapiont>
			<year>2009</year>
			<specialname>人力资源管理</specialname>
			<maxfs>584</maxfs>
			<varfs>584</varfs>
			<minfs>--</minfs>
			<pc>一批</pc>
			<stype>文科</stype>
		</areapiont>
	    <areapiont>
			<year>2008</year>
			<specialname>英语</specialname>
			<maxfs>540</maxfs>
			<varfs>540</varfs>
			<minfs></minfs>
			<pc>一批</pc>
			<stype>文科</stype>
		</areapiont>
	    <areapiont>
			<year>2005</year>
			<specialname>市场营销</specialname>
			<maxfs>555</maxfs>
			<varfs>555</varfs>
			<minfs>--</minfs>
			<pc>一批</pc>
			<stype>文科</stype>
		</areapiont>
</areapionts>