<?xml version="1.0" encoding="UTF-8" ?>
   <scores>
	         	          	<score>
	              <year>2016</year>
	              <maxScore>--</maxScore>
	              <avgScore>523</avgScore>
	              <minScore>--</minScore>
	              <ps>465</ps>
	              <fc>58</fc>
	              <rb>一批</rb>
	              <rs>0</rs>
	               <ph>238</ph>
	              </score>
	          	<score>
	              <year>2015</year>
	              <maxScore>602</maxScore>
	              <avgScore>575</avgScore>
	              <minScore>--</minScore>
	              <ps>525</ps>
	              <fc>50</fc>
	              <rb>一批</rb>
	              <rs>25</rs>
	               <ph>238</ph>
	              </score>
	          	<score>
	              <year>2014</year>
	              <maxScore>--</maxScore>
	              <avgScore>542</avgScore>
	              <minScore>--</minScore>
	              <ps>506</ps>
	              <fc>36</fc>
	              <rb>一批</rb>
	              <rs>20</rs>
	               <ph>238</ph>
	              </score>
	          	<score>
	              <year>2013</year>
	              <maxScore>566</maxScore>
	              <avgScore>548</avgScore>
	              <minScore>--</minScore>
	              <ps>501</ps>
	              <fc>47</fc>
	              <rb>一批</rb>
	              <rs>26</rs>
	               <ph>238</ph>
	              </score>
	          	<score>
	              <year>2012</year>
	              <maxScore>587</maxScore>
	              <avgScore>581</avgScore>
	              <minScore>--</minScore>
	              <ps>546</ps>
	              <fc>35</fc>
	              <rb>一批</rb>
	              <rs>16</rs>
	               <ph>238</ph>
	              </score>
	          	<score>
	              <year>2011</year>
	              <maxScore>620</maxScore>
	              <avgScore>606</avgScore>
	              <minScore>--</minScore>
	              <ps>573</ps>
	              <fc>33</fc>
	              <rb>一批</rb>
	              <rs>16</rs>
	               <ph>238</ph>
	              </score>
	          	<score>
	              <year>2010</year>
	              <maxScore>574</maxScore>
	              <avgScore>558</avgScore>
	              <minScore>--</minScore>
	              <ps>539</ps>
	              <fc>19</fc>
	              <rb>一批</rb>
	              <rs>0</rs>
	               <ph>238</ph>
	              </score>
	          	<score>
	              <year>2009</year>
	              <maxScore>614</maxScore>
	              <avgScore>593</avgScore>
	              <minScore>--</minScore>
	              <ps>569</ps>
	              <fc>24</fc>
	              <rb>一批</rb>
	              <rs>0</rs>
	               <ph>238</ph>
	              </score>
	          	<score>
	              <year>2008</year>
	              <maxScore>577</maxScore>
	              <avgScore>551</avgScore>
	              <minScore>--</minScore>
	              <ps>534</ps>
	              <fc>17</fc>
	              <rb>一批</rb>
	              <rs>0</rs>
	               <ph>238</ph>
	              </score>
	          	<score>
	              <year>2007</year>
	              <maxScore>600</maxScore>
	              <avgScore>584</avgScore>
	              <minScore>--</minScore>
	              <ps>562</ps>
	              <fc>22</fc>
	              <rb>一批</rb>
	              <rs>0</rs>
	               <ph>238</ph>
	              </score>
	          	<score>
	              <year>2006</year>
	              <maxScore>591</maxScore>
	              <avgScore>578</avgScore>
	              <minScore>--</minScore>
	              <ps>561</ps>
	              <fc>17</fc>
	              <rb>一批</rb>
	              <rs>0</rs>
	               <ph>238</ph>
	              </score>
	          	<score>
	              <year>2005</year>
	              <maxScore>574</maxScore>
	              <avgScore>--</avgScore>
	              <minScore>--</minScore>
	              <ps></ps>
	              <fc>0</fc>
	              <rb>一批</rb>
	              <rs>0</rs>
	               <ph>238</ph>
	              </score>
   </scores>