<?xml version="1.0" encoding="UTF-8" ?>
   <scores>
	         	          	<score>
	              <year>2016</year>
	              <maxScore>--</maxScore>
	              <avgScore>542</avgScore>
	              <minScore>--</minScore>
	              <ps>465</ps>
	              <fc>77</fc>
	              <rb>一批</rb>
	              <rs>0</rs>
	               <ph>517</ph>
	              </score>
	          	<score>
	              <year>2015</year>
	              <maxScore>610</maxScore>
	              <avgScore>585</avgScore>
	              <minScore>--</minScore>
	              <ps>525</ps>
	              <fc>60</fc>
	              <rb>一批</rb>
	              <rs>29</rs>
	               <ph>517</ph>
	              </score>
	          	<score>
	              <year>2014</year>
	              <maxScore>605</maxScore>
	              <avgScore>598</avgScore>
	              <minScore>591</minScore>
	              <ps>506</ps>
	              <fc>92</fc>
	              <rb>一批</rb>
	              <rs>23</rs>
	               <ph>517</ph>
	              </score>
	          	<score>
	              <year>2013</year>
	              <maxScore>560</maxScore>
	              <avgScore>541</avgScore>
	              <minScore>521</minScore>
	              <ps>501</ps>
	              <fc>40</fc>
	              <rb>一批</rb>
	              <rs>17</rs>
	               <ph>517</ph>
	              </score>
	          	<score>
	              <year>2012</year>
	              <maxScore>599</maxScore>
	              <avgScore>581</avgScore>
	              <minScore>565</minScore>
	              <ps>546</ps>
	              <fc>35</fc>
	              <rb>一批</rb>
	              <rs>25</rs>
	               <ph>517</ph>
	              </score>
	          	<score>
	              <year>2011</year>
	              <maxScore>603</maxScore>
	              <avgScore>590</avgScore>
	              <minScore>575</minScore>
	              <ps>573</ps>
	              <fc>17</fc>
	              <rb>一批</rb>
	              <rs>22</rs>
	               <ph>517</ph>
	              </score>
	          	<score>
	              <year>2010</year>
	              <maxScore>583</maxScore>
	              <avgScore>566</avgScore>
	              <minScore>--</minScore>
	              <ps>539</ps>
	              <fc>27</fc>
	              <rb>一批</rb>
	              <rs>0</rs>
	               <ph>517</ph>
	              </score>
	          	<score>
	              <year>2009</year>
	              <maxScore>619</maxScore>
	              <avgScore>591</avgScore>
	              <minScore>--</minScore>
	              <ps>569</ps>
	              <fc>22</fc>
	              <rb>一批</rb>
	              <rs>0</rs>
	               <ph>517</ph>
	              </score>
	          	<score>
	              <year>2008</year>
	              <maxScore>567</maxScore>
	              <avgScore>552</avgScore>
	              <minScore>--</minScore>
	              <ps>534</ps>
	              <fc>18</fc>
	              <rb>一批</rb>
	              <rs>0</rs>
	               <ph>517</ph>
	              </score>
	          	<score>
	              <year>2007</year>
	              <maxScore>611</maxScore>
	              <avgScore>575</avgScore>
	              <minScore>--</minScore>
	              <ps>562</ps>
	              <fc>13</fc>
	              <rb>一批</rb>
	              <rs>0</rs>
	               <ph>517</ph>
	              </score>
   </scores>