<?xml version="1.0" encoding="UTF-8" ?>
   <scores>
	         	          	<score>
	              <year>2016</year>
	              <maxScore>--</maxScore>
	              <avgScore>462</avgScore>
	              <minScore>--</minScore>
	              <ps>403</ps>
	              <fc>59</fc>
	              <rb>二批</rb>
	              <rs>0</rs>
	               <ph>384</ph>
	              </score>
	          	<score>
	              <year>2015</year>
	              <maxScore>517</maxScore>
	              <avgScore>514</avgScore>
	              <minScore>--</minScore>
	              <ps>462</ps>
	              <fc>52</fc>
	              <rb>二批</rb>
	              <rs>4</rs>
	               <ph>384</ph>
	              </score>
	          	<score>
	              <year>2014</year>
	              <maxScore>--</maxScore>
	              <avgScore>533</avgScore>
	              <minScore>--</minScore>
	              <ps>482</ps>
	              <fc>51</fc>
	              <rb>二批</rb>
	              <rs>7</rs>
	               <ph>384</ph>
	              </score>
	          	<score>
	              <year>2013</year>
	              <maxScore>487</maxScore>
	              <avgScore>481</avgScore>
	              <minScore>--</minScore>
	              <ps>431</ps>
	              <fc>50</fc>
	              <rb>二批</rb>
	              <rs>8</rs>
	               <ph>384</ph>
	              </score>
	          	<score>
	              <year>2012</year>
	              <maxScore>530</maxScore>
	              <avgScore>519</avgScore>
	              <minScore>--</minScore>
	              <ps>466</ps>
	              <fc>53</fc>
	              <rb>二批</rb>
	              <rs>11</rs>
	               <ph>384</ph>
	              </score>
	          	<score>
	              <year>2011</year>
	              <maxScore>533</maxScore>
	              <avgScore>525</avgScore>
	              <minScore>--</minScore>
	              <ps>473</ps>
	              <fc>52</fc>
	              <rb>二批</rb>
	              <rs>8</rs>
	               <ph>384</ph>
	              </score>
	          	<score>
	              <year>2010</year>
	              <maxScore>529</maxScore>
	              <avgScore>520</avgScore>
	              <minScore>--</minScore>
	              <ps>494</ps>
	              <fc>26</fc>
	              <rb>二批</rb>
	              <rs>0</rs>
	               <ph>384</ph>
	              </score>
	          	<score>
	              <year>2009</year>
	              <maxScore>544</maxScore>
	              <avgScore>529</avgScore>
	              <minScore>--</minScore>
	              <ps>518</ps>
	              <fc>11</fc>
	              <rb>二批</rb>
	              <rs>0</rs>
	               <ph>384</ph>
	              </score>
	          	<score>
	              <year>2007</year>
	              <maxScore>538</maxScore>
	              <avgScore>517</avgScore>
	              <minScore>--</minScore>
	              <ps>505</ps>
	              <fc>12</fc>
	              <rb>二批</rb>
	              <rs>0</rs>
	               <ph>384</ph>
	              </score>
   </scores>