<?xml version="1.0" encoding="utf-8" ?>
<areapionts>
    	    <areapiont>
			<year>2014</year>
			<specialname>针灸推拿学</specialname>
			<maxfs>--</maxfs>
			<varfs>563</varfs>
			<minfs>--</minfs>
			<pc>一批</pc>
			<stype>文科</stype>
		</areapiont>
	    <areapiont>
			<year>2014</year>
			<specialname>护理学</specialname>
			<maxfs>--</maxfs>
			<varfs>556</varfs>
			<minfs>--</minfs>
			<pc>一批</pc>
			<stype>文科</stype>
		</areapiont>
	    <areapiont>
			<year>2014</year>
			<specialname>中医学</specialname>
			<maxfs>--</maxfs>
			<varfs>556</varfs>
			<minfs>--</minfs>
			<pc>一批</pc>
			<stype>文科</stype>
		</areapiont>
	    <areapiont>
			<year>2016</year>
			<specialname>中医学</specialname>
			<maxfs>--</maxfs>
			<varfs>497</varfs>
			<minfs>--</minfs>
			<pc>二批</pc>
			<stype>文科</stype>
		</areapiont>
	    <areapiont>
			<year>2016</year>
			<specialname>护理学类</specialname>
			<maxfs>--</maxfs>
			<varfs>413</varfs>
			<minfs>--</minfs>
			<pc>二批</pc>
			<stype>文科</stype>
		</areapiont>
	    <areapiont>
			<year>2016</year>
			<specialname>针灸推拿学</specialname>
			<maxfs>--</maxfs>
			<varfs>480</varfs>
			<minfs>--</minfs>
			<pc>二批</pc>
			<stype>文科</stype>
		</areapiont>
	    <areapiont>
			<year>2016</year>
			<specialname>公共事业管理</specialname>
			<maxfs>--</maxfs>
			<varfs>469</varfs>
			<minfs>--</minfs>
			<pc>二批</pc>
			<stype>文科</stype>
		</areapiont>
	    <areapiont>
			<year>2015</year>
			<specialname>中医学</specialname>
			<maxfs>546</maxfs>
			<varfs>546</varfs>
			<minfs>546</minfs>
			<pc>二批</pc>
			<stype>文科</stype>
		</areapiont>
	    <areapiont>
			<year>2015</year>
			<specialname>针灸推拿学</specialname>
			<maxfs>542</maxfs>
			<varfs>542</varfs>
			<minfs>542</minfs>
			<pc>二批</pc>
			<stype>文科</stype>
		</areapiont>
	    <areapiont>
			<year>2015</year>
			<specialname>康复治疗学</specialname>
			<maxfs>541</maxfs>
			<varfs>541</varfs>
			<minfs>541</minfs>
			<pc>二批</pc>
			<stype>文科</stype>
		</areapiont>
	    <areapiont>
			<year>2015</year>
			<specialname>护理学类</specialname>
			<maxfs>493</maxfs>
			<varfs>493</varfs>
			<minfs>493</minfs>
			<pc>二批</pc>
			<stype>文科</stype>
		</areapiont>
	    <areapiont>
			<year>2015</year>
			<specialname>公共事业管理</specialname>
			<maxfs>535</maxfs>
			<varfs>535</varfs>
			<minfs>535</minfs>
			<pc>二批</pc>
			<stype>文科</stype>
		</areapiont>
</areapionts>