<?xml version="1.0" encoding="UTF-8" ?>
   <scores>
	         	          	<score>
	              <year>2011</year>
	              <maxScore>413</maxScore>
	              <avgScore>315</avgScore>
	              <minScore>272</minScore>
	              <ps>473</ps>
	              <fc>-158</fc>
	              <rb>二批</rb>
	              <rs>0</rs>
	               <ph>1515</ph>
	              </score>
	          	<score>
	              <year>2010</year>
	              <maxScore>361</maxScore>
	              <avgScore>335</avgScore>
	              <minScore>279</minScore>
	              <ps>494</ps>
	              <fc>-159</fc>
	              <rb>二批</rb>
	              <rs>0</rs>
	               <ph>1515</ph>
	              </score>
   </scores>