<?xml version="1.0" encoding="UTF-8" ?>
   <scores>
	         	          	<score>
	              <year>2010</year>
	              <maxScore>508</maxScore>
	              <avgScore>496</avgScore>
	              <minScore>--</minScore>
	              <ps>464</ps>
	              <fc>32</fc>
	              <rb>三批</rb>
	              <rs>0</rs>
	               <ph>711</ph>
	              </score>
	          	<score>
	              <year>2009</year>
	              <maxScore>513</maxScore>
	              <avgScore>510</avgScore>
	              <minScore>--</minScore>
	              <ps>481</ps>
	              <fc>29</fc>
	              <rb>三批</rb>
	              <rs>0</rs>
	               <ph>711</ph>
	              </score>
	          	<score>
	              <year>2008</year>
	              <maxScore>490</maxScore>
	              <avgScore>482</avgScore>
	              <minScore>--</minScore>
	              <ps>452</ps>
	              <fc>30</fc>
	              <rb>三批</rb>
	              <rs>0</rs>
	               <ph>711</ph>
	              </score>
   </scores>