<?xml version="1.0" encoding="utf-8" ?>
<areapionts>
    	    <areapiont>
			<year>2014</year>
			<specialname>社会工作</specialname>
			<maxfs>--</maxfs>
			<varfs>526</varfs>
			<minfs>--</minfs>
			<pc>一批</pc>
			<stype>文科</stype>
		</areapiont>
	    <areapiont>
			<year>2014</year>
			<specialname>工商管理</specialname>
			<maxfs>--</maxfs>
			<varfs>535</varfs>
			<minfs>--</minfs>
			<pc>一批</pc>
			<stype>文科</stype>
		</areapiont>
	    <areapiont>
			<year>2013</year>
			<specialname>工商管理</specialname>
			<maxfs>477</maxfs>
			<varfs>475</varfs>
			<minfs>--</minfs>
			<pc>二批</pc>
			<stype>文科</stype>
		</areapiont>
	    <areapiont>
			<year>2013</year>
			<specialname>社会工作</specialname>
			<maxfs>468</maxfs>
			<varfs>463</varfs>
			<minfs>--</minfs>
			<pc>二批</pc>
			<stype>文科</stype>
		</areapiont>
	    <areapiont>
			<year>2012</year>
			<specialname>社会工作</specialname>
			<maxfs>512</maxfs>
			<varfs>512</varfs>
			<minfs>--</minfs>
			<pc>二批</pc>
			<stype>文科</stype>
		</areapiont>
	    <areapiont>
			<year>2012</year>
			<specialname>工商管理</specialname>
			<maxfs>513</maxfs>
			<varfs>513</varfs>
			<minfs>--</minfs>
			<pc>二批</pc>
			<stype>文科</stype>
		</areapiont>
	    <areapiont>
			<year>2011</year>
			<specialname>社会工作</specialname>
			<maxfs>517</maxfs>
			<varfs>509</varfs>
			<minfs>0</minfs>
			<pc>二批</pc>
			<stype>文科</stype>
		</areapiont>
	    <areapiont>
			<year>2011</year>
			<specialname>工商管理</specialname>
			<maxfs>511</maxfs>
			<varfs>510</varfs>
			<minfs>0</minfs>
			<pc>二批</pc>
			<stype>文科</stype>
		</areapiont>
	    <areapiont>
			<year>2010</year>
			<specialname>社会工作</specialname>
			<maxfs>507</maxfs>
			<varfs>507</varfs>
			<minfs>--</minfs>
			<pc>二批</pc>
			<stype>文科</stype>
		</areapiont>
	    <areapiont>
			<year>2009</year>
			<specialname>社会工作</specialname>
			<maxfs>554</maxfs>
			<varfs>549</varfs>
			<minfs>--</minfs>
			<pc>二批</pc>
			<stype>文科</stype>
		</areapiont>
	    <areapiont>
			<year>2008</year>
			<specialname>社会工作</specialname>
			<maxfs>491</maxfs>
			<varfs>491</varfs>
			<minfs></minfs>
			<pc>二批</pc>
			<stype>文科</stype>
		</areapiont>
	    <areapiont>
			<year>2007</year>
			<specialname>社会工作</specialname>
			<maxfs>550</maxfs>
			<varfs>549</varfs>
			<minfs>--</minfs>
			<pc>二批</pc>
			<stype>文科</stype>
		</areapiont>
	    <areapiont>
			<year>2006</year>
			<specialname>社会工作</specialname>
			<maxfs>542</maxfs>
			<varfs>540</varfs>
			<minfs>--</minfs>
			<pc>二批</pc>
			<stype>文科</stype>
		</areapiont>
	    <areapiont>
			<year>2005</year>
			<specialname>社会工作</specialname>
			<maxfs>544</maxfs>
			<varfs>519</varfs>
			<minfs>--</minfs>
			<pc>二批</pc>
			<stype>文科</stype>
		</areapiont>
</areapionts>