<?xml version="1.0" encoding="utf-8" ?>
<areapionts>
    	    <areapiont>
			<year>2014</year>
			<specialname>会计学</specialname>
			<maxfs>--</maxfs>
			<varfs>485</varfs>
			<minfs>--</minfs>
			<pc>一批</pc>
			<stype>文科</stype>
		</areapiont>
	    <areapiont>
			<year>2016</year>
			<specialname>会计学</specialname>
			<maxfs>--</maxfs>
			<varfs>405</varfs>
			<minfs>--</minfs>
			<pc>二批</pc>
			<stype>文科</stype>
		</areapiont>
	    <areapiont>
			<year>2015</year>
			<specialname>会计学</specialname>
			<maxfs>505</maxfs>
			<varfs>484</varfs>
			<minfs>462</minfs>
			<pc>二批</pc>
			<stype>文科</stype>
		</areapiont>
	    <areapiont>
			<year>2012</year>
			<specialname>国际经济与贸易</specialname>
			<maxfs>469</maxfs>
			<varfs>469</varfs>
			<minfs>--</minfs>
			<pc>二批</pc>
			<stype>文科</stype>
		</areapiont>
	    <areapiont>
			<year>2012</year>
			<specialname>广告学</specialname>
			<maxfs>468</maxfs>
			<varfs>468</varfs>
			<minfs>--</minfs>
			<pc>二批</pc>
			<stype>文科</stype>
		</areapiont>
	    <areapiont>
			<year>2012</year>
			<specialname>市场营销</specialname>
			<maxfs>467</maxfs>
			<varfs>467</varfs>
			<minfs>--</minfs>
			<pc>二批</pc>
			<stype>文科</stype>
		</areapiont>
	    <areapiont>
			<year>2012</year>
			<specialname>会计学</specialname>
			<maxfs>474</maxfs>
			<varfs>474</varfs>
			<minfs>--</minfs>
			<pc>二批</pc>
			<stype>文科</stype>
		</areapiont>
	    <areapiont>
			<year>2011</year>
			<specialname>广告学</specialname>
			<maxfs>474</maxfs>
			<varfs>474</varfs>
			<minfs>0</minfs>
			<pc>二批</pc>
			<stype>文科</stype>
		</areapiont>
	    <areapiont>
			<year>2009</year>
			<specialname>广告学</specialname>
			<maxfs>486</maxfs>
			<varfs>484</varfs>
			<minfs>--</minfs>
			<pc>三批</pc>
			<stype>文科</stype>
		</areapiont>
	    <areapiont>
			<year>2008</year>
			<specialname>英语</specialname>
			<maxfs>466</maxfs>
			<varfs>462</varfs>
			<minfs></minfs>
			<pc>三批</pc>
			<stype>文科</stype>
		</areapiont>
	    <areapiont>
			<year>2008</year>
			<specialname>对外汉语</specialname>
			<maxfs>473</maxfs>
			<varfs>467</varfs>
			<minfs></minfs>
			<pc>三批</pc>
			<stype>文科</stype>
		</areapiont>
	    <areapiont>
			<year>2008</year>
			<specialname>会计学</specialname>
			<maxfs>480</maxfs>
			<varfs>480</varfs>
			<minfs></minfs>
			<pc>三批</pc>
			<stype>文科</stype>
		</areapiont>
	    <areapiont>
			<year>2008</year>
			<specialname>国际经济与贸易</specialname>
			<maxfs>464</maxfs>
			<varfs>464</varfs>
			<minfs></minfs>
			<pc>三批</pc>
			<stype>文科</stype>
		</areapiont>
	    <areapiont>
			<year>2008</year>
			<specialname>广告学</specialname>
			<maxfs>465</maxfs>
			<varfs>465</varfs>
			<minfs></minfs>
			<pc>三批</pc>
			<stype>文科</stype>
		</areapiont>
	    <areapiont>
			<year>2008</year>
			<specialname>市场营销</specialname>
			<maxfs>484</maxfs>
			<varfs>484</varfs>
			<minfs></minfs>
			<pc>三批</pc>
			<stype>文科</stype>
		</areapiont>
	    <areapiont>
			<year>2007</year>
			<specialname>国际经济与贸易</specialname>
			<maxfs>537</maxfs>
			<varfs>537</varfs>
			<minfs>--</minfs>
			<pc>三批</pc>
			<stype>文科</stype>
		</areapiont>
	    <areapiont>
			<year>2007</year>
			<specialname>市场营销</specialname>
			<maxfs>535</maxfs>
			<varfs>535</varfs>
			<minfs>--</minfs>
			<pc>三批</pc>
			<stype>文科</stype>
		</areapiont>
	    <areapiont>
			<year>2007</year>
			<specialname>英语</specialname>
			<maxfs>541</maxfs>
			<varfs>505</varfs>
			<minfs>--</minfs>
			<pc>三批</pc>
			<stype>文科</stype>
		</areapiont>
	    <areapiont>
			<year>2007</year>
			<specialname>会计学</specialname>
			<maxfs>544</maxfs>
			<varfs>544</varfs>
			<minfs>--</minfs>
			<pc>三批</pc>
			<stype>文科</stype>
		</areapiont>
	    <areapiont>
			<year>2007</year>
			<specialname>汉语言文学</specialname>
			<maxfs>525</maxfs>
			<varfs>522</varfs>
			<minfs>--</minfs>
			<pc>三批</pc>
			<stype>文科</stype>
		</areapiont>
</areapionts>