<?xml version="1.0" encoding="utf-8" ?>
<areapionts>
    	    <areapiont>
			<year>2015</year>
			<specialname>中国语言文学类</specialname>
			<maxfs>535</maxfs>
			<varfs>521</varfs>
			<minfs>509</minfs>
			<pc>二批</pc>
			<stype>文科</stype>
		</areapiont>
	    <areapiont>
			<year>2013</year>
			<specialname>公共事业管理</specialname>
			<maxfs>470</maxfs>
			<varfs>468</varfs>
			<minfs>--</minfs>
			<pc>二批</pc>
			<stype>文科</stype>
		</areapiont>
	    <areapiont>
			<year>2012</year>
			<specialname>公共事业管理</specialname>
			<maxfs>490</maxfs>
			<varfs>483</varfs>
			<minfs>--</minfs>
			<pc>二批</pc>
			<stype>文科</stype>
		</areapiont>
	    <areapiont>
			<year>2016</year>
			<specialname>英语</specialname>
			<maxfs>--</maxfs>
			<varfs>420</varfs>
			<minfs>--</minfs>
			<pc>提前</pc>
			<stype>文科</stype>
		</areapiont>
	    <areapiont>
			<year>2016</year>
			<specialname>教育学类</specialname>
			<maxfs>--</maxfs>
			<varfs>421</varfs>
			<minfs>--</minfs>
			<pc>提前</pc>
			<stype>文科</stype>
		</areapiont>
	    <areapiont>
			<year>2016</year>
			<specialname>思想政治教育</specialname>
			<maxfs>--</maxfs>
			<varfs>438</varfs>
			<minfs>--</minfs>
			<pc>提前</pc>
			<stype>文科</stype>
		</areapiont>
</areapionts>